AIScratch/Genetic/__init__.py
AIScratch/Genetic/genetic_algorithm.py
AIScratch/NeuralNetwork/ActivationFunctions/__init__.py
AIScratch/NeuralNetwork/ActivationFunctions/function.py
AIScratch/NeuralNetwork/ActivationFunctions/linear.py
AIScratch/NeuralNetwork/ActivationFunctions/relu.py
AIScratch/NeuralNetwork/ActivationFunctions/sigmoide.py
AIScratch/NeuralNetwork/ActivationFunctions/softmax.py
AIScratch/NeuralNetwork/ActivationFunctions/treshold.py
AIScratch/NeuralNetwork/Encoders/__init__.py
AIScratch/NeuralNetwork/Encoders/encoder.py
AIScratch/NeuralNetwork/Encoders/minmax_scaling.py
AIScratch/NeuralNetwork/ErrorFunctions/__init__.py
AIScratch/NeuralNetwork/ErrorFunctions/cross_entropy.py
AIScratch/NeuralNetwork/ErrorFunctions/function.py
AIScratch/NeuralNetwork/ErrorFunctions/hinge_loss.py
AIScratch/NeuralNetwork/ErrorFunctions/mse.py
AIScratch/NeuralNetwork/Layers/__init__.py
AIScratch/NeuralNetwork/Layers/dense.py
AIScratch/NeuralNetwork/Layers/dropout.py
AIScratch/NeuralNetwork/Layers/layer.py
AIScratch/NeuralNetwork/MLP/__init__.py
AIScratch/NeuralNetwork/MLP/multi_layer_perceptron.py
AIScratch/NeuralNetwork/Optimizers/__init__.py
AIScratch/NeuralNetwork/Optimizers/adam.py
AIScratch/NeuralNetwork/Optimizers/optimizer.py
AIScratch/NeuralNetwork/Optimizers/sgd.py
AIScratch/NeuralNetwork/Perceptron/__init__.py
AIScratch/NeuralNetwork/Perceptron/perceptron.py
AIScratch/NeuralNetwork/SpatialLayers/__init__.py
AIScratch/NeuralNetwork/SpatialLayers/conv2d.py
AIScratch/NeuralNetwork/SpatialLayers/flatten.py
AIScratch/NeuralNetwork/SpatialLayers/pooling.py
AIScratch/NeuralNetwork/SpatialLayers/spatial_layer.py
AIScratch/NeuralNetwork/__init__.py
AIScratch/__init__.py
aiscratch-1.0.1.dist-info/METADATA
aiscratch-1.0.1.dist-info/WHEEL
aiscratch-1.0.1.dist-info/RECORD
